MANIFEST.in
VERSION
requirements.txt
setup.py
docs/source/conf.py
examples/simple_ops.py
unimatrix.ext.blob.egg-info/PKG-INFO
unimatrix.ext.blob.egg-info/SOURCES.txt
unimatrix.ext.blob.egg-info/dependency_links.txt
unimatrix.ext.blob.egg-info/requires.txt
unimatrix.ext.blob.egg-info/top_level.txt
unimatrix/ext/blob/__init__.py
unimatrix/ext/blob/package.json
unimatrix/ext/blob/backends/__init__.py
unimatrix/ext/blob/backends/azure.py
unimatrix/ext/blob/backends/base.py
unimatrix/ext/blob/backends/istoragebackend.py
unimatrix/ext/blob/backends/local.py
unimatrix/ext/blob/backends/pointer.py
unimatrix/ext/blob/backends/tests/__init__.py
unimatrix/ext/blob/backends/tests/base.py
unimatrix/ext/blob/backends/tests/test_integration_azure.py
unimatrix/ext/blob/backends/tests/test_integration_local.py
unimatrix/ext/blob/backends/tests/test_unit_local.py
unimatrix/ext/blob/tests/test_integration_noop.py
unimatrix/ext/blob/tests/test_system_noop.py
unimatrix/ext/blob/tests/test_unit_noop.py